check_type_wrapper/__init__.py
check_type_wrapper/_version.py
check_type_wrapper/check_type.py
check_type_wrapper/discrepancy_item.py
check_type_wrapper/exception.py
tests/__init__.py
tests/test_wrapper.py
Quastrado_check_type_wrapper-1.0.0.dist-info/LICENSE
Quastrado_check_type_wrapper-1.0.0.dist-info/METADATA
Quastrado_check_type_wrapper-1.0.0.dist-info/WHEEL
Quastrado_check_type_wrapper-1.0.0.dist-info/top_level.txt
Quastrado_check_type_wrapper-1.0.0.dist-info/RECORD
