Metadata-Version: 2.1
Name: Quastrado-check-type-wrapper
Version: 1.0.0
Summary: A simple decorator to control the type matching of the arguments passed     
Home-page: https://github.com/Quastrado/check_type_wrapper
Author: Quastrado
Author-email: quastrado@gmail.com
License: UNKNOWN
Platform: UNKNOWN
